pytest_datafiles.py
pytest_datafiles-3.0.1.dist-info/METADATA
pytest_datafiles-3.0.1.dist-info/WHEEL
pytest_datafiles-3.0.1.dist-info/entry_points.txt
pytest_datafiles-3.0.1.dist-info/licenses/LICENSE
pytest_datafiles-3.0.1.dist-info/RECORD
