Metadata-Version: 2.4
Name: pytest-datafiles
Version: 3.0.1
Summary: py.test plugin to create a 'tmp_path' containing predefined files/directories.
Project-URL: Homepage, https://github.com/omarkohl/pytest-datafiles
Project-URL: Repository, https://github.com/omarkohl/pytest-datafiles
Project-URL: Issues, https://github.com/omarkohl/pytest-datafiles/issues
Author-email: Omar Kohl <omarkohl@gmail.com>
Maintainer-email: Omar Kohl <omarkohl@gmail.com>
License-Expression: MIT
License-File: LICENSE
Keywords: datafiles,pytest,tmp_path
Classifier: Development Status :: 5 - Production/Stable
Classifier: Framework :: Pytest
Classifier: Intended Audience :: Developers
Classifier: License :: OSI Approved :: MIT License
Classifier: Operating System :: OS Independent
Classifier: Programming Language :: Python :: 3
Classifier: Programming Language :: Python :: 3.8
Classifier: Programming Language :: Python :: 3.9
Classifier: Programming Language :: Python :: 3.10
Classifier: Programming Language :: Python :: 3.11
Classifier: Programming Language :: Python :: 3.12
Classifier: Programming Language :: Python :: 3.13
Classifier: Topic :: Software Development :: Testing
Requires-Python: >=3.8
Requires-Dist: pytest>=6.2.0
